smartfileorganizerny/main.py
smartfileorganizerny/utils/__init__.py
smartfileorganizerny/utils/exceptions.py
smartfileorganizerny/utils/logger.py
smartfileorganizerny/utils/organizer.py
smartfileorganizerny-0.1.5.dist-info/licenses/LICENSE
smartfileorganizerny-0.1.5.dist-info/METADATA
smartfileorganizerny-0.1.5.dist-info/WHEEL
smartfileorganizerny-0.1.5.dist-info/entry_points.txt
smartfileorganizerny-0.1.5.dist-info/top_level.txt
smartfileorganizerny-0.1.5.dist-info/RECORD
