Metadata-Version: 2.4
Name: smartfileorganizerny
Version: 0.1.5
Summary: Organize your files by type or date automatically
Author-email: Nikhil Yakkala <nikhilyakkala@gmail.com>
License: MIT License
Requires-Python: >=3.8
License-File: LICENSE
Requires-Dist: colorlog
Dynamic: license-file
